{
    "sections": {
        "appetizers": {
            "title": "Appetizers",
            "description": "Traditional Vietnamese small eats.",
            "items": [
                {
                    "id": "item-spring-rolls",
                    "title": "Spring Rolls - Goi Cuon",
                    "description": "Rice vermicelli & lettuce rolled in fresh rice paper with your choice of Shrimp, Chicken, or Tofu. Served with peanut sauce.",
                    "variants": [
                        {
                            "id": "variant-spring-rolls-with-shrimp",
                            "title": "Spring Rolls with Shrimp",
                            "base_price": 100,
                            "available": true
                        },
                        {
                            "id": "variant-spring-rolls-with-chicken",
                            "title": "Spring Rolls with Chicken",
                            "base_price": 100,
                            "available": true
                        },
                        {
                            "id": "variant-spring-rolls-with-tofu",
                            "title": "Spring Rolls with Tofu",
                            "base_price": 100,
                            "available": true
                        }
                    ],
                    "add_ons": [
                        {
                            "id": "add-egg",
                            "add_price": 100
                        }
                    ],
                    "sizes": null
                },
                {
                    "id": "item-vegetarian-egg-rolls",
                    "title": "Vegetarian Egg Rolls",
                    "description": "Deep fried roll filled with tofu, noodles, onions, carrots, and taro. Served with fish sauce.",
                    "variants": [
                        {
                            "id": "variant-vegetarian-egg-rolls",
                            "title": "Vegetarian Egg Rolls",
                            "base_price": 100,
                            "available": true
                        }
                    ],
                    "sizes": null
                },
                {
                    "id": "item-banh-mi",
                    "title": "Vietnamese Sandwich (Banh Mi)",
                    "description": "Fresh baguette filled with shredded carrots, cucumbers, cilantro, and your choice of BBQ Pork, Chicken, or Tofu.",
                    "variants": [
                        {
                            "id": "variant-banh-mi-with-pork",
                            "title": "Banh Mi with BBQ Pork",
                            "base_price": 100,
                            "available": true
                        },
                        {
                            "id": "variant-banh-mi-with-chicken",
                            "title": "Banh Mi with Chicken",
                            "base_price": 100,
                            "available": true
                        },
                        {
                            "id": "variant-banh-mi-with-tofu",
                            "title": "Banh Mi with Tofu",
                            "base_price": 100,
                            "available": true
                        }
                    ],
                    "add_ons": [
                        {
                            "id": "add-egg",
                            "add_price": 100
                        },
                        {
                            "id": "extra-meat",
                            "add_price": 100
                        }
                    ],
                    "sizes": null
                }
            ]
        },
        "pho": {
            "title": "Pho",
            "description": "Rice noodle soup with your choice of meat, seafood, or tofu. Served with beansprouts, basil, and lime. Size comes in small or large.",
            "items": [
                {
                    "id": "item-pho-with-beef",
                    "title": "Pho with Beef",
                    "variants": [
                        {
                            "id": "variant-pho-with-beef",
                            "title": "Pho with Beef",
                            "base_price": 100,
                            "available": true
                        }
                    ],
                    "add_ons": [
                        {
                            "id": "extra-meat",
                            "add_price": 100
                        }
                    ],
                    "sizes": [
                        {
                            "id": "small",
                            "add_price": 100
                        },
                        {
                            "id": "large",
                            "add_price": 200
                        }
                    ]
                }
            ]
        }
    }
}